information_composer/__init__.py
information_composer/core/__init__.py
information_composer/core/doi_downloader.py
information_composer/core/downloader.py
information_composer/core/utils/__init__.py
information_composer/llm_filter/__init__.py
information_composer/llm_filter/cli/__init__.py
information_composer/llm_filter/cli/main.py
information_composer/llm_filter/config/__init__.py
information_composer/llm_filter/config/settings.py
information_composer/llm_filter/core/__init__.py
information_composer/llm_filter/core/extractor.py
information_composer/llm_filter/core/filter.py
information_composer/llm_filter/core/parser.py
information_composer/llm_filter/llm/__init__.py
information_composer/llm_filter/llm/dashscope_client.py
information_composer/llm_filter/llm/llm_interface.py
information_composer/llm_filter/utils/__init__.py
information_composer/llm_filter/utils/markdown_utils.py
information_composer/llm_filter/utils/text_processing.py
information_composer/markdown/__init__.py
information_composer/markdown/markdown.py
information_composer/markdown/vendor/__init__.py
information_composer/markdown/vendor/CommonMark/CommonMark.py
information_composer/markdown/vendor/CommonMark/__init__.py
information_composer/markdown/vendor/CommonMark/entitytrans.py
information_composer/markdown/vendor/CommonMark/test/test-CommonMark.py
information_composer/markdown/vendor/docopt/__init__.py
information_composer/markdown/vendor/docopt/_version.py
information_composer/markdown/vendor/docopt/py.typed
information_composer/pdf/__init__.py
information_composer/pdf/validator.py
information_composer/pdf/cli/__init__.py
information_composer/pdf/cli/main.py
information_composer/pubmed/__init__.py
information_composer/pubmed/baseline.py
information_composer/pubmed/litsense.py
information_composer/pubmed/pubmed.py
information_composer/pubmed/py.typed
information_composer/pubmed/analyzer/__init__.py
information_composer/pubmed/analyzer/analyzer.py
information_composer/pubmed/analyzer/cache.py
information_composer-0.2.1.dist-info/licenses/LICENSE
information_composer-0.2.1.dist-info/METADATA
information_composer-0.2.1.dist-info/WHEEL
information_composer-0.2.1.dist-info/entry_points.txt
information_composer-0.2.1.dist-info/top_level.txt
information_composer-0.2.1.dist-info/RECORD
