Metadata-Version: 2.4
Name: information-composer
Version: 0.2.1
Summary: A comprehensive toolkit for collecting, composing, and filtering information from various web resources with AI-powered markdown processing
Author-email: Tao Zhang <forrest_zhang@163.com>
License: MIT License
Project-URL: Homepage, https://github.com/yourusername/information-composer
Project-URL: Documentation, https://information-composer.readthedocs.io/
Project-URL: Repository, https://github.com/yourusername/information-composer.git
Project-URL: Issues, https://github.com/yourusername/information-composer/issues
Keywords: web scraping,information collection,data composition,markdown,llm,filter,academic,paper,nlp,ai,dashscope,llama-index
Classifier: Development Status :: 3 - Alpha
Classifier: Intended Audience :: Developers
Classifier: License :: OSI Approved :: MIT License
Classifier: Programming Language :: Python :: 3
Classifier: Programming Language :: Python :: 3.12
Classifier: Programming Language :: Python :: 3.13
Classifier: Operating System :: OS Independent
Requires-Python: >=3.12
License-File: LICENSE
Requires-Dist: requests>=2.28.0
Requires-Dist: beautifulsoup4>=4.11.0
Requires-Dist: habanero>=1.2.0
Requires-Dist: pandas>=2.2.0
Requires-Dist: pubmed-parser>=0.5.0
Requires-Dist: biopython>=1.84
Requires-Dist: pony>=0.7.17
Requires-Dist: llama-index>=0.10.0
Requires-Dist: dashscope>=1.14.0
Requires-Dist: pydantic>=2.0.0
Requires-Dist: llama-index-llms-dashscope>=0.1.0
Requires-Dist: markdown>=3.5.0
Requires-Dist: lxml>=4.9.0
Requires-Dist: nltk>=3.8.0
Requires-Dist: spacy>=3.7.0
Requires-Dist: python-dotenv>=1.0.0
Requires-Dist: pyyaml>=6.0.0
Requires-Dist: aiohttp>=3.8.0
Requires-Dist: asyncio-throttle>=1.0.0
Requires-Dist: aiofiles>=23.0.0
Requires-Dist: pypdfium2>=4.0.0
Requires-Dist: feedparser>=6.0.0
Requires-Dist: python-dateutil>=2.8.0
Requires-Dist: click>=8.0.0
Requires-Dist: langchain>=0.1.0
Requires-Dist: langchain-core>=0.1.0
Provides-Extra: dev
Requires-Dist: pytest>=7.0; extra == "dev"
Requires-Dist: pytest-cov>=3.0; extra == "dev"
Requires-Dist: black>=22.0; extra == "dev"
Requires-Dist: isort>=5.0; extra == "dev"
Requires-Dist: ruff>=0.1.0; extra == "dev"
Requires-Dist: mypy>=1.0; extra == "dev"
Requires-Dist: types-requests; extra == "dev"
Requires-Dist: types-beautifulsoup4; extra == "dev"
Requires-Dist: types-PyYAML; extra == "dev"
Dynamic: license-file
